{"loss": 128.98309428623745, "epoch": 0, "time_this_iter_s": 29.893020629882812, "done": false, "timesteps_total": null, "episodes_total": null, "training_iteration": 1, "experiment_id": "4705856e011f477eb062cc3ecd55c165", "date": "2021-03-02_23-21-18", "timestamp": 1614727278, "time_total_s": 29.893020629882812, "pid": 8500, "hostname": "instance-adlr-2", "node_ip": "10.128.0.5", "config": {"model": "CVAE", "robot": "Planar", "dof": 6, "len_links": [0.5, 0.5, 0.5, 0.5, 0.5, 1.0], "results_dir": "results/", "input_dim": 6, "condition_dim": 2, "latent_dim": 4, "num_layers": 3, "hidden_dim": 200, "num_epochs": 60, "batch_size": 1000, "lr_rate": 0.0041583305116809416, "weight_decay": 1.0073364581245354e-05, "variational_beta": 0.0067, "checkpoint_epoch": 0, "hyperparam_tuning": true}, "time_since_restore": 29.893020629882812, "timesteps_since_restore": 0, "iterations_since_restore": 1, "trial_id": "f6f23_00005"}
{"loss": 70.31482645307268, "epoch": 1, "time_this_iter_s": 20.95106029510498, "done": false, "timesteps_total": null, "episodes_total": null, "training_iteration": 2, "experiment_id": "4705856e011f477eb062cc3ecd55c165", "date": "2021-03-02_23-21-39", "timestamp": 1614727299, "time_total_s": 50.84408092498779, "pid": 8500, "hostname": "instance-adlr-2", "node_ip": "10.128.0.5", "config": {"model": "CVAE", "robot": "Planar", "dof": 6, "len_links": [0.5, 0.5, 0.5, 0.5, 0.5, 1.0], "results_dir": "results/", "input_dim": 6, "condition_dim": 2, "latent_dim": 4, "num_layers": 3, "hidden_dim": 200, "num_epochs": 60, "batch_size": 1000, "lr_rate": 0.0041583305116809416, "weight_decay": 1.0073364581245354e-05, "variational_beta": 0.0067, "checkpoint_epoch": 0, "hyperparam_tuning": true}, "time_since_restore": 50.84408092498779, "timesteps_since_restore": 0, "iterations_since_restore": 2, "trial_id": "f6f23_00005"}
{"loss": 67.96617644718715, "epoch": 2, "time_this_iter_s": 20.48676109313965, "done": false, "timesteps_total": null, "episodes_total": null, "training_iteration": 3, "experiment_id": "4705856e011f477eb062cc3ecd55c165", "date": "2021-03-02_23-21-59", "timestamp": 1614727319, "time_total_s": 71.33084201812744, "pid": 8500, "hostname": "instance-adlr-2", "node_ip": "10.128.0.5", "config": {"model": "CVAE", "robot": "Planar", "dof": 6, "len_links": [0.5, 0.5, 0.5, 0.5, 0.5, 1.0], "results_dir": "results/", "input_dim": 6, "condition_dim": 2, "latent_dim": 4, "num_layers": 3, "hidden_dim": 200, "num_epochs": 60, "batch_size": 1000, "lr_rate": 0.0041583305116809416, "weight_decay": 1.0073364581245354e-05, "variational_beta": 0.0067, "checkpoint_epoch": 0, "hyperparam_tuning": true}, "time_since_restore": 71.33084201812744, "timesteps_since_restore": 0, "iterations_since_restore": 3, "trial_id": "f6f23_00005"}
{"loss": 61.30951783316476, "epoch": 3, "time_this_iter_s": 20.70810842514038, "done": false, "timesteps_total": null, "episodes_total": null, "training_iteration": 4, "experiment_id": "4705856e011f477eb062cc3ecd55c165", "date": "2021-03-02_23-22-20", "timestamp": 1614727340, "time_total_s": 92.03895044326782, "pid": 8500, "hostname": "instance-adlr-2", "node_ip": "10.128.0.5", "config": {"model": "CVAE", "robot": "Planar", "dof": 6, "len_links": [0.5, 0.5, 0.5, 0.5, 0.5, 1.0], "results_dir": "results/", "input_dim": 6, "condition_dim": 2, "latent_dim": 4, "num_layers": 3, "hidden_dim": 200, "num_epochs": 60, "batch_size": 1000, "lr_rate": 0.0041583305116809416, "weight_decay": 1.0073364581245354e-05, "variational_beta": 0.0067, "checkpoint_epoch": 0, "hyperparam_tuning": true}, "time_since_restore": 92.03895044326782, "timesteps_since_restore": 0, "iterations_since_restore": 4, "trial_id": "f6f23_00005"}
{"loss": 61.509511462620324, "epoch": 4, "time_this_iter_s": 20.317993879318237, "done": false, "timesteps_total": null, "episodes_total": null, "training_iteration": 5, "experiment_id": "4705856e011f477eb062cc3ecd55c165", "date": "2021-03-02_23-22-40", "timestamp": 1614727360, "time_total_s": 112.35694432258606, "pid": 8500, "hostname": "instance-adlr-2", "node_ip": "10.128.0.5", "config": {"model": "CVAE", "robot": "Planar", "dof": 6, "len_links": [0.5, 0.5, 0.5, 0.5, 0.5, 1.0], "results_dir": "results/", "input_dim": 6, "condition_dim": 2, "latent_dim": 4, "num_layers": 3, "hidden_dim": 200, "num_epochs": 60, "batch_size": 1000, "lr_rate": 0.0041583305116809416, "weight_decay": 1.0073364581245354e-05, "variational_beta": 0.0067, "checkpoint_epoch": 0, "hyperparam_tuning": true}, "time_since_restore": 112.35694432258606, "timesteps_since_restore": 0, "iterations_since_restore": 5, "trial_id": "f6f23_00005"}
{"loss": 56.46361068725586, "epoch": 5, "time_this_iter_s": 20.728533029556274, "done": false, "timesteps_total": null, "episodes_total": null, "training_iteration": 6, "experiment_id": "4705856e011f477eb062cc3ecd55c165", "date": "2021-03-02_23-23-01", "timestamp": 1614727381, "time_total_s": 133.08547735214233, "pid": 8500, "hostname": "instance-adlr-2", "node_ip": "10.128.0.5", "config": {"model": "CVAE", "robot": "Planar", "dof": 6, "len_links": [0.5, 0.5, 0.5, 0.5, 0.5, 1.0], "results_dir": "results/", "input_dim": 6, "condition_dim": 2, "latent_dim": 4, "num_layers": 3, "hidden_dim": 200, "num_epochs": 60, "batch_size": 1000, "lr_rate": 0.0041583305116809416, "weight_decay": 1.0073364581245354e-05, "variational_beta": 0.0067, "checkpoint_epoch": 0, "hyperparam_tuning": true}, "time_since_restore": 133.08547735214233, "timesteps_since_restore": 0, "iterations_since_restore": 6, "trial_id": "f6f23_00005"}
{"loss": 54.82935179574149, "epoch": 6, "time_this_iter_s": 20.054677724838257, "done": false, "timesteps_total": null, "episodes_total": null, "training_iteration": 7, "experiment_id": "4705856e011f477eb062cc3ecd55c165", "date": "2021-03-02_23-23-21", "timestamp": 1614727401, "time_total_s": 153.1401550769806, "pid": 8500, "hostname": "instance-adlr-2", "node_ip": "10.128.0.5", "config": {"model": "CVAE", "robot": "Planar", "dof": 6, "len_links": [0.5, 0.5, 0.5, 0.5, 0.5, 1.0], "results_dir": "results/", "input_dim": 6, "condition_dim": 2, "latent_dim": 4, "num_layers": 3, "hidden_dim": 200, "num_epochs": 60, "batch_size": 1000, "lr_rate": 0.0041583305116809416, "weight_decay": 1.0073364581245354e-05, "variational_beta": 0.0067, "checkpoint_epoch": 0, "hyperparam_tuning": true}, "time_since_restore": 153.1401550769806, "timesteps_since_restore": 0, "iterations_since_restore": 7, "trial_id": "f6f23_00005"}
{"loss": 54.047804990495955, "epoch": 7, "time_this_iter_s": 19.9936044216156, "done": false, "timesteps_total": null, "episodes_total": null, "training_iteration": 8, "experiment_id": "4705856e011f477eb062cc3ecd55c165", "date": "2021-03-02_23-23-41", "timestamp": 1614727421, "time_total_s": 173.1337594985962, "pid": 8500, "hostname": "instance-adlr-2", "node_ip": "10.128.0.5", "config": {"model": "CVAE", "robot": "Planar", "dof": 6, "len_links": [0.5, 0.5, 0.5, 0.5, 0.5, 1.0], "results_dir": "results/", "input_dim": 6, "condition_dim": 2, "latent_dim": 4, "num_layers": 3, "hidden_dim": 200, "num_epochs": 60, "batch_size": 1000, "lr_rate": 0.0041583305116809416, "weight_decay": 1.0073364581245354e-05, "variational_beta": 0.0067, "checkpoint_epoch": 0, "hyperparam_tuning": true}, "time_since_restore": 173.1337594985962, "timesteps_since_restore": 0, "iterations_since_restore": 8, "trial_id": "f6f23_00005"}
{"loss": 53.07333535330636, "epoch": 8, "time_this_iter_s": 20.90421438217163, "done": false, "timesteps_total": null, "episodes_total": null, "training_iteration": 9, "experiment_id": "4705856e011f477eb062cc3ecd55c165", "date": "2021-03-02_23-24-02", "timestamp": 1614727442, "time_total_s": 194.03797388076782, "pid": 8500, "hostname": "instance-adlr-2", "node_ip": "10.128.0.5", "config": {"model": "CVAE", "robot": "Planar", "dof": 6, "len_links": [0.5, 0.5, 0.5, 0.5, 0.5, 1.0], "results_dir": "results/", "input_dim": 6, "condition_dim": 2, "latent_dim": 4, "num_layers": 3, "hidden_dim": 200, "num_epochs": 60, "batch_size": 1000, "lr_rate": 0.0041583305116809416, "weight_decay": 1.0073364581245354e-05, "variational_beta": 0.0067, "checkpoint_epoch": 0, "hyperparam_tuning": true}, "time_since_restore": 194.03797388076782, "timesteps_since_restore": 0, "iterations_since_restore": 9, "trial_id": "f6f23_00005"}
{"loss": 53.698768114362444, "epoch": 9, "time_this_iter_s": 20.784517526626587, "done": false, "timesteps_total": null, "episodes_total": null, "training_iteration": 10, "experiment_id": "4705856e011f477eb062cc3ecd55c165", "date": "2021-03-02_23-24-23", "timestamp": 1614727463, "time_total_s": 214.8224914073944, "pid": 8500, "hostname": "instance-adlr-2", "node_ip": "10.128.0.5", "config": {"model": "CVAE", "robot": "Planar", "dof": 6, "len_links": [0.5, 0.5, 0.5, 0.5, 0.5, 1.0], "results_dir": "results/", "input_dim": 6, "condition_dim": 2, "latent_dim": 4, "num_layers": 3, "hidden_dim": 200, "num_epochs": 60, "batch_size": 1000, "lr_rate": 0.0041583305116809416, "weight_decay": 1.0073364581245354e-05, "variational_beta": 0.0067, "checkpoint_epoch": 0, "hyperparam_tuning": true}, "time_since_restore": 214.8224914073944, "timesteps_since_restore": 0, "iterations_since_restore": 10, "trial_id": "f6f23_00005"}
{"loss": 53.61682676587786, "epoch": 10, "time_this_iter_s": 19.208297967910767, "done": false, "timesteps_total": null, "episodes_total": null, "training_iteration": 11, "experiment_id": "4705856e011f477eb062cc3ecd55c165", "date": "2021-03-02_23-24-42", "timestamp": 1614727482, "time_total_s": 234.03078937530518, "pid": 8500, "hostname": "instance-adlr-2", "node_ip": "10.128.0.5", "config": {"model": "CVAE", "robot": "Planar", "dof": 6, "len_links": [0.5, 0.5, 0.5, 0.5, 0.5, 1.0], "results_dir": "results/", "input_dim": 6, "condition_dim": 2, "latent_dim": 4, "num_layers": 3, "hidden_dim": 200, "num_epochs": 60, "batch_size": 1000, "lr_rate": 0.0041583305116809416, "weight_decay": 1.0073364581245354e-05, "variational_beta": 0.0067, "checkpoint_epoch": 0, "hyperparam_tuning": true}, "time_since_restore": 234.03078937530518, "timesteps_since_restore": 0, "iterations_since_restore": 11, "trial_id": "f6f23_00005"}
{"loss": 53.03067046574184, "epoch": 11, "time_this_iter_s": 21.032723426818848, "done": false, "timesteps_total": null, "episodes_total": null, "training_iteration": 12, "experiment_id": "4705856e011f477eb062cc3ecd55c165", "date": "2021-03-02_23-25-03", "timestamp": 1614727503, "time_total_s": 255.06351280212402, "pid": 8500, "hostname": "instance-adlr-2", "node_ip": "10.128.0.5", "config": {"model": "CVAE", "robot": "Planar", "dof": 6, "len_links": [0.5, 0.5, 0.5, 0.5, 0.5, 1.0], "results_dir": "results/", "input_dim": 6, "condition_dim": 2, "latent_dim": 4, "num_layers": 3, "hidden_dim": 200, "num_epochs": 60, "batch_size": 1000, "lr_rate": 0.0041583305116809416, "weight_decay": 1.0073364581245354e-05, "variational_beta": 0.0067, "checkpoint_epoch": 0, "hyperparam_tuning": true}, "time_since_restore": 255.06351280212402, "timesteps_since_restore": 0, "iterations_since_restore": 12, "trial_id": "f6f23_00005"}
{"loss": 52.17260340554374, "epoch": 12, "time_this_iter_s": 19.576364517211914, "done": false, "timesteps_total": null, "episodes_total": null, "training_iteration": 13, "experiment_id": "4705856e011f477eb062cc3ecd55c165", "date": "2021-03-02_23-25-22", "timestamp": 1614727522, "time_total_s": 274.63987731933594, "pid": 8500, "hostname": "instance-adlr-2", "node_ip": "10.128.0.5", "config": {"model": "CVAE", "robot": "Planar", "dof": 6, "len_links": [0.5, 0.5, 0.5, 0.5, 0.5, 1.0], "results_dir": "results/", "input_dim": 6, "condition_dim": 2, "latent_dim": 4, "num_layers": 3, "hidden_dim": 200, "num_epochs": 60, "batch_size": 1000, "lr_rate": 0.0041583305116809416, "weight_decay": 1.0073364581245354e-05, "variational_beta": 0.0067, "checkpoint_epoch": 0, "hyperparam_tuning": true}, "time_since_restore": 274.63987731933594, "timesteps_since_restore": 0, "iterations_since_restore": 13, "trial_id": "f6f23_00005"}
{"loss": 52.08225304194859, "epoch": 13, "time_this_iter_s": 20.413955688476562, "done": false, "timesteps_total": null, "episodes_total": null, "training_iteration": 14, "experiment_id": "4705856e011f477eb062cc3ecd55c165", "date": "2021-03-02_23-25-43", "timestamp": 1614727543, "time_total_s": 295.0538330078125, "pid": 8500, "hostname": "instance-adlr-2", "node_ip": "10.128.0.5", "config": {"model": "CVAE", "robot": "Planar", "dof": 6, "len_links": [0.5, 0.5, 0.5, 0.5, 0.5, 1.0], "results_dir": "results/", "input_dim": 6, "condition_dim": 2, "latent_dim": 4, "num_layers": 3, "hidden_dim": 200, "num_epochs": 60, "batch_size": 1000, "lr_rate": 0.0041583305116809416, "weight_decay": 1.0073364581245354e-05, "variational_beta": 0.0067, "checkpoint_epoch": 0, "hyperparam_tuning": true}, "time_since_restore": 295.0538330078125, "timesteps_since_restore": 0, "iterations_since_restore": 14, "trial_id": "f6f23_00005"}
{"loss": 52.45701914106097, "epoch": 14, "time_this_iter_s": 20.002342700958252, "done": false, "timesteps_total": null, "episodes_total": null, "training_iteration": 15, "experiment_id": "4705856e011f477eb062cc3ecd55c165", "date": "2021-03-02_23-26-03", "timestamp": 1614727563, "time_total_s": 315.05617570877075, "pid": 8500, "hostname": "instance-adlr-2", "node_ip": "10.128.0.5", "config": {"model": "CVAE", "robot": "Planar", "dof": 6, "len_links": [0.5, 0.5, 0.5, 0.5, 0.5, 1.0], "results_dir": "results/", "input_dim": 6, "condition_dim": 2, "latent_dim": 4, "num_layers": 3, "hidden_dim": 200, "num_epochs": 60, "batch_size": 1000, "lr_rate": 0.0041583305116809416, "weight_decay": 1.0073364581245354e-05, "variational_beta": 0.0067, "checkpoint_epoch": 0, "hyperparam_tuning": true}, "time_since_restore": 315.05617570877075, "timesteps_since_restore": 0, "iterations_since_restore": 15, "trial_id": "f6f23_00005"}
{"loss": 51.98135500771659, "epoch": 15, "time_this_iter_s": 20.51629066467285, "done": false, "timesteps_total": null, "episodes_total": null, "training_iteration": 16, "experiment_id": "4705856e011f477eb062cc3ecd55c165", "date": "2021-03-02_23-26-23", "timestamp": 1614727583, "time_total_s": 335.5724663734436, "pid": 8500, "hostname": "instance-adlr-2", "node_ip": "10.128.0.5", "config": {"model": "CVAE", "robot": "Planar", "dof": 6, "len_links": [0.5, 0.5, 0.5, 0.5, 0.5, 1.0], "results_dir": "results/", "input_dim": 6, "condition_dim": 2, "latent_dim": 4, "num_layers": 3, "hidden_dim": 200, "num_epochs": 60, "batch_size": 1000, "lr_rate": 0.0041583305116809416, "weight_decay": 1.0073364581245354e-05, "variational_beta": 0.0067, "checkpoint_epoch": 0, "hyperparam_tuning": true}, "time_since_restore": 335.5724663734436, "timesteps_since_restore": 0, "iterations_since_restore": 16, "trial_id": "f6f23_00005"}
{"loss": 51.97919003077916, "epoch": 16, "time_this_iter_s": 19.681453227996826, "done": false, "timesteps_total": null, "episodes_total": null, "training_iteration": 17, "experiment_id": "4705856e011f477eb062cc3ecd55c165", "date": "2021-03-02_23-26-43", "timestamp": 1614727603, "time_total_s": 355.25391960144043, "pid": 8500, "hostname": "instance-adlr-2", "node_ip": "10.128.0.5", "config": {"model": "CVAE", "robot": "Planar", "dof": 6, "len_links": [0.5, 0.5, 0.5, 0.5, 0.5, 1.0], "results_dir": "results/", "input_dim": 6, "condition_dim": 2, "latent_dim": 4, "num_layers": 3, "hidden_dim": 200, "num_epochs": 60, "batch_size": 1000, "lr_rate": 0.0041583305116809416, "weight_decay": 1.0073364581245354e-05, "variational_beta": 0.0067, "checkpoint_epoch": 0, "hyperparam_tuning": true}, "time_since_restore": 355.25391960144043, "timesteps_since_restore": 0, "iterations_since_restore": 17, "trial_id": "f6f23_00005"}
{"loss": 51.52928726196289, "epoch": 17, "time_this_iter_s": 19.984368324279785, "done": false, "timesteps_total": null, "episodes_total": null, "training_iteration": 18, "experiment_id": "4705856e011f477eb062cc3ecd55c165", "date": "2021-03-02_23-27-03", "timestamp": 1614727623, "time_total_s": 375.2382879257202, "pid": 8500, "hostname": "instance-adlr-2", "node_ip": "10.128.0.5", "config": {"model": "CVAE", "robot": "Planar", "dof": 6, "len_links": [0.5, 0.5, 0.5, 0.5, 0.5, 1.0], "results_dir": "results/", "input_dim": 6, "condition_dim": 2, "latent_dim": 4, "num_layers": 3, "hidden_dim": 200, "num_epochs": 60, "batch_size": 1000, "lr_rate": 0.0041583305116809416, "weight_decay": 1.0073364581245354e-05, "variational_beta": 0.0067, "checkpoint_epoch": 0, "hyperparam_tuning": true}, "time_since_restore": 375.2382879257202, "timesteps_since_restore": 0, "iterations_since_restore": 18, "trial_id": "f6f23_00005"}
{"loss": 51.909749685014994, "epoch": 18, "time_this_iter_s": 18.884859085083008, "done": false, "timesteps_total": null, "episodes_total": null, "training_iteration": 19, "experiment_id": "4705856e011f477eb062cc3ecd55c165", "date": "2021-03-02_23-27-22", "timestamp": 1614727642, "time_total_s": 394.1231470108032, "pid": 8500, "hostname": "instance-adlr-2", "node_ip": "10.128.0.5", "config": {"model": "CVAE", "robot": "Planar", "dof": 6, "len_links": [0.5, 0.5, 0.5, 0.5, 0.5, 1.0], "results_dir": "results/", "input_dim": 6, "condition_dim": 2, "latent_dim": 4, "num_layers": 3, "hidden_dim": 200, "num_epochs": 60, "batch_size": 1000, "lr_rate": 0.0041583305116809416, "weight_decay": 1.0073364581245354e-05, "variational_beta": 0.0067, "checkpoint_epoch": 0, "hyperparam_tuning": true}, "time_since_restore": 394.1231470108032, "timesteps_since_restore": 0, "iterations_since_restore": 19, "trial_id": "f6f23_00005"}
{"loss": 51.64964232308524, "epoch": 19, "time_this_iter_s": 19.901068210601807, "done": false, "timesteps_total": null, "episodes_total": null, "training_iteration": 20, "experiment_id": "4705856e011f477eb062cc3ecd55c165", "date": "2021-03-02_23-27-42", "timestamp": 1614727662, "time_total_s": 414.02421522140503, "pid": 8500, "hostname": "instance-adlr-2", "node_ip": "10.128.0.5", "config": {"model": "CVAE", "robot": "Planar", "dof": 6, "len_links": [0.5, 0.5, 0.5, 0.5, 0.5, 1.0], "results_dir": "results/", "input_dim": 6, "condition_dim": 2, "latent_dim": 4, "num_layers": 3, "hidden_dim": 200, "num_epochs": 60, "batch_size": 1000, "lr_rate": 0.0041583305116809416, "weight_decay": 1.0073364581245354e-05, "variational_beta": 0.0067, "checkpoint_epoch": 0, "hyperparam_tuning": true}, "time_since_restore": 414.02421522140503, "timesteps_since_restore": 0, "iterations_since_restore": 20, "trial_id": "f6f23_00005"}
{"loss": 51.177496343340195, "epoch": 20, "time_this_iter_s": 20.179648637771606, "done": false, "timesteps_total": null, "episodes_total": null, "training_iteration": 21, "experiment_id": "4705856e011f477eb062cc3ecd55c165", "date": "2021-03-02_23-28-02", "timestamp": 1614727682, "time_total_s": 434.20386385917664, "pid": 8500, "hostname": "instance-adlr-2", "node_ip": "10.128.0.5", "config": {"model": "CVAE", "robot": "Planar", "dof": 6, "len_links": [0.5, 0.5, 0.5, 0.5, 0.5, 1.0], "results_dir": "results/", "input_dim": 6, "condition_dim": 2, "latent_dim": 4, "num_layers": 3, "hidden_dim": 200, "num_epochs": 60, "batch_size": 1000, "lr_rate": 0.0041583305116809416, "weight_decay": 1.0073364581245354e-05, "variational_beta": 0.0067, "checkpoint_epoch": 0, "hyperparam_tuning": true}, "time_since_restore": 434.20386385917664, "timesteps_since_restore": 0, "iterations_since_restore": 21, "trial_id": "f6f23_00005"}
{"loss": 51.42015354701451, "epoch": 21, "time_this_iter_s": 19.382534980773926, "done": false, "timesteps_total": null, "episodes_total": null, "training_iteration": 22, "experiment_id": "4705856e011f477eb062cc3ecd55c165", "date": "2021-03-02_23-28-21", "timestamp": 1614727701, "time_total_s": 453.58639883995056, "pid": 8500, "hostname": "instance-adlr-2", "node_ip": "10.128.0.5", "config": {"model": "CVAE", "robot": "Planar", "dof": 6, "len_links": [0.5, 0.5, 0.5, 0.5, 0.5, 1.0], "results_dir": "results/", "input_dim": 6, "condition_dim": 2, "latent_dim": 4, "num_layers": 3, "hidden_dim": 200, "num_epochs": 60, "batch_size": 1000, "lr_rate": 0.0041583305116809416, "weight_decay": 1.0073364581245354e-05, "variational_beta": 0.0067, "checkpoint_epoch": 0, "hyperparam_tuning": true}, "time_since_restore": 453.58639883995056, "timesteps_since_restore": 0, "iterations_since_restore": 22, "trial_id": "f6f23_00005"}
{"loss": 51.42620284489223, "epoch": 22, "time_this_iter_s": 19.271608114242554, "done": false, "timesteps_total": null, "episodes_total": null, "training_iteration": 23, "experiment_id": "4705856e011f477eb062cc3ecd55c165", "date": "2021-03-02_23-28-41", "timestamp": 1614727721, "time_total_s": 472.8580069541931, "pid": 8500, "hostname": "instance-adlr-2", "node_ip": "10.128.0.5", "config": {"model": "CVAE", "robot": "Planar", "dof": 6, "len_links": [0.5, 0.5, 0.5, 0.5, 0.5, 1.0], "results_dir": "results/", "input_dim": 6, "condition_dim": 2, "latent_dim": 4, "num_layers": 3, "hidden_dim": 200, "num_epochs": 60, "batch_size": 1000, "lr_rate": 0.0041583305116809416, "weight_decay": 1.0073364581245354e-05, "variational_beta": 0.0067, "checkpoint_epoch": 0, "hyperparam_tuning": true}, "time_since_restore": 472.8580069541931, "timesteps_since_restore": 0, "iterations_since_restore": 23, "trial_id": "f6f23_00005"}
{"loss": 51.36175119127546, "epoch": 23, "time_this_iter_s": 17.550187826156616, "done": false, "timesteps_total": null, "episodes_total": null, "training_iteration": 24, "experiment_id": "4705856e011f477eb062cc3ecd55c165", "date": "2021-03-02_23-28-58", "timestamp": 1614727738, "time_total_s": 490.40819478034973, "pid": 8500, "hostname": "instance-adlr-2", "node_ip": "10.128.0.5", "config": {"model": "CVAE", "robot": "Planar", "dof": 6, "len_links": [0.5, 0.5, 0.5, 0.5, 0.5, 1.0], "results_dir": "results/", "input_dim": 6, "condition_dim": 2, "latent_dim": 4, "num_layers": 3, "hidden_dim": 200, "num_epochs": 60, "batch_size": 1000, "lr_rate": 0.0041583305116809416, "weight_decay": 1.0073364581245354e-05, "variational_beta": 0.0067, "checkpoint_epoch": 0, "hyperparam_tuning": true}, "time_since_restore": 490.40819478034973, "timesteps_since_restore": 0, "iterations_since_restore": 24, "trial_id": "f6f23_00005"}
{"loss": 51.333082749503, "epoch": 24, "time_this_iter_s": 19.912755250930786, "done": false, "timesteps_total": null, "episodes_total": null, "training_iteration": 25, "experiment_id": "4705856e011f477eb062cc3ecd55c165", "date": "2021-03-02_23-29-18", "timestamp": 1614727758, "time_total_s": 510.3209500312805, "pid": 8500, "hostname": "instance-adlr-2", "node_ip": "10.128.0.5", "config": {"model": "CVAE", "robot": "Planar", "dof": 6, "len_links": [0.5, 0.5, 0.5, 0.5, 0.5, 1.0], "results_dir": "results/", "input_dim": 6, "condition_dim": 2, "latent_dim": 4, "num_layers": 3, "hidden_dim": 200, "num_epochs": 60, "batch_size": 1000, "lr_rate": 0.0041583305116809416, "weight_decay": 1.0073364581245354e-05, "variational_beta": 0.0067, "checkpoint_epoch": 0, "hyperparam_tuning": true}, "time_since_restore": 510.3209500312805, "timesteps_since_restore": 0, "iterations_since_restore": 25, "trial_id": "f6f23_00005"}
{"loss": 51.5647575378418, "epoch": 25, "time_this_iter_s": 19.695446014404297, "done": false, "timesteps_total": null, "episodes_total": null, "training_iteration": 26, "experiment_id": "4705856e011f477eb062cc3ecd55c165", "date": "2021-03-02_23-29-38", "timestamp": 1614727778, "time_total_s": 530.0163960456848, "pid": 8500, "hostname": "instance-adlr-2", "node_ip": "10.128.0.5", "config": {"model": "CVAE", "robot": "Planar", "dof": 6, "len_links": [0.5, 0.5, 0.5, 0.5, 0.5, 1.0], "results_dir": "results/", "input_dim": 6, "condition_dim": 2, "latent_dim": 4, "num_layers": 3, "hidden_dim": 200, "num_epochs": 60, "batch_size": 1000, "lr_rate": 0.0041583305116809416, "weight_decay": 1.0073364581245354e-05, "variational_beta": 0.0067, "checkpoint_epoch": 0, "hyperparam_tuning": true}, "time_since_restore": 530.0163960456848, "timesteps_since_restore": 0, "iterations_since_restore": 26, "trial_id": "f6f23_00005"}
{"loss": 52.19038697923933, "epoch": 26, "time_this_iter_s": 19.43668556213379, "done": false, "timesteps_total": null, "episodes_total": null, "training_iteration": 27, "experiment_id": "4705856e011f477eb062cc3ecd55c165", "date": "2021-03-02_23-29-57", "timestamp": 1614727797, "time_total_s": 549.4530816078186, "pid": 8500, "hostname": "instance-adlr-2", "node_ip": "10.128.0.5", "config": {"model": "CVAE", "robot": "Planar", "dof": 6, "len_links": [0.5, 0.5, 0.5, 0.5, 0.5, 1.0], "results_dir": "results/", "input_dim": 6, "condition_dim": 2, "latent_dim": 4, "num_layers": 3, "hidden_dim": 200, "num_epochs": 60, "batch_size": 1000, "lr_rate": 0.0041583305116809416, "weight_decay": 1.0073364581245354e-05, "variational_beta": 0.0067, "checkpoint_epoch": 0, "hyperparam_tuning": true}, "time_since_restore": 549.4530816078186, "timesteps_since_restore": 0, "iterations_since_restore": 27, "trial_id": "f6f23_00005"}
{"loss": 52.92075030190604, "epoch": 27, "time_this_iter_s": 19.361074686050415, "done": false, "timesteps_total": null, "episodes_total": null, "training_iteration": 28, "experiment_id": "4705856e011f477eb062cc3ecd55c165", "date": "2021-03-02_23-30-17", "timestamp": 1614727817, "time_total_s": 568.814156293869, "pid": 8500, "hostname": "instance-adlr-2", "node_ip": "10.128.0.5", "config": {"model": "CVAE", "robot": "Planar", "dof": 6, "len_links": [0.5, 0.5, 0.5, 0.5, 0.5, 1.0], "results_dir": "results/", "input_dim": 6, "condition_dim": 2, "latent_dim": 4, "num_layers": 3, "hidden_dim": 200, "num_epochs": 60, "batch_size": 1000, "lr_rate": 0.0041583305116809416, "weight_decay": 1.0073364581245354e-05, "variational_beta": 0.0067, "checkpoint_epoch": 0, "hyperparam_tuning": true}, "time_since_restore": 568.814156293869, "timesteps_since_restore": 0, "iterations_since_restore": 28, "trial_id": "f6f23_00005"}
{"loss": 52.6887258039202, "epoch": 28, "time_this_iter_s": 19.732306718826294, "done": false, "timesteps_total": null, "episodes_total": null, "training_iteration": 29, "experiment_id": "4705856e011f477eb062cc3ecd55c165", "date": "2021-03-02_23-30-36", "timestamp": 1614727836, "time_total_s": 588.5464630126953, "pid": 8500, "hostname": "instance-adlr-2", "node_ip": "10.128.0.5", "config": {"model": "CVAE", "robot": "Planar", "dof": 6, "len_links": [0.5, 0.5, 0.5, 0.5, 0.5, 1.0], "results_dir": "results/", "input_dim": 6, "condition_dim": 2, "latent_dim": 4, "num_layers": 3, "hidden_dim": 200, "num_epochs": 60, "batch_size": 1000, "lr_rate": 0.0041583305116809416, "weight_decay": 1.0073364581245354e-05, "variational_beta": 0.0067, "checkpoint_epoch": 0, "hyperparam_tuning": true}, "time_since_restore": 588.5464630126953, "timesteps_since_restore": 0, "iterations_since_restore": 29, "trial_id": "f6f23_00005"}
{"loss": 51.42900948115758, "epoch": 29, "time_this_iter_s": 19.76628565788269, "done": false, "timesteps_total": null, "episodes_total": null, "training_iteration": 30, "experiment_id": "4705856e011f477eb062cc3ecd55c165", "date": "2021-03-02_23-30-56", "timestamp": 1614727856, "time_total_s": 608.312748670578, "pid": 8500, "hostname": "instance-adlr-2", "node_ip": "10.128.0.5", "config": {"model": "CVAE", "robot": "Planar", "dof": 6, "len_links": [0.5, 0.5, 0.5, 0.5, 0.5, 1.0], "results_dir": "results/", "input_dim": 6, "condition_dim": 2, "latent_dim": 4, "num_layers": 3, "hidden_dim": 200, "num_epochs": 60, "batch_size": 1000, "lr_rate": 0.0041583305116809416, "weight_decay": 1.0073364581245354e-05, "variational_beta": 0.0067, "checkpoint_epoch": 0, "hyperparam_tuning": true}, "time_since_restore": 608.312748670578, "timesteps_since_restore": 0, "iterations_since_restore": 30, "trial_id": "f6f23_00005"}
{"loss": 51.11786337171282, "epoch": 30, "time_this_iter_s": 19.399560689926147, "done": false, "timesteps_total": null, "episodes_total": null, "training_iteration": 31, "experiment_id": "4705856e011f477eb062cc3ecd55c165", "date": "2021-03-02_23-31-15", "timestamp": 1614727875, "time_total_s": 627.7123093605042, "pid": 8500, "hostname": "instance-adlr-2", "node_ip": "10.128.0.5", "config": {"model": "CVAE", "robot": "Planar", "dof": 6, "len_links": [0.5, 0.5, 0.5, 0.5, 0.5, 1.0], "results_dir": "results/", "input_dim": 6, "condition_dim": 2, "latent_dim": 4, "num_layers": 3, "hidden_dim": 200, "num_epochs": 60, "batch_size": 1000, "lr_rate": 0.0041583305116809416, "weight_decay": 1.0073364581245354e-05, "variational_beta": 0.0067, "checkpoint_epoch": 0, "hyperparam_tuning": true}, "time_since_restore": 627.7123093605042, "timesteps_since_restore": 0, "iterations_since_restore": 31, "trial_id": "f6f23_00005"}
{"loss": 50.96223256792341, "epoch": 31, "time_this_iter_s": 19.648050546646118, "done": false, "timesteps_total": null, "episodes_total": null, "training_iteration": 32, "experiment_id": "4705856e011f477eb062cc3ecd55c165", "date": "2021-03-02_23-31-35", "timestamp": 1614727895, "time_total_s": 647.3603599071503, "pid": 8500, "hostname": "instance-adlr-2", "node_ip": "10.128.0.5", "config": {"model": "CVAE", "robot": "Planar", "dof": 6, "len_links": [0.5, 0.5, 0.5, 0.5, 0.5, 1.0], "results_dir": "results/", "input_dim": 6, "condition_dim": 2, "latent_dim": 4, "num_layers": 3, "hidden_dim": 200, "num_epochs": 60, "batch_size": 1000, "lr_rate": 0.0041583305116809416, "weight_decay": 1.0073364581245354e-05, "variational_beta": 0.0067, "checkpoint_epoch": 0, "hyperparam_tuning": true}, "time_since_restore": 647.3603599071503, "timesteps_since_restore": 0, "iterations_since_restore": 32, "trial_id": "f6f23_00005"}
{"loss": 50.91527478899275, "epoch": 32, "time_this_iter_s": 19.47805380821228, "done": false, "timesteps_total": null, "episodes_total": null, "training_iteration": 33, "experiment_id": "4705856e011f477eb062cc3ecd55c165", "date": "2021-03-02_23-31-55", "timestamp": 1614727915, "time_total_s": 666.8384137153625, "pid": 8500, "hostname": "instance-adlr-2", "node_ip": "10.128.0.5", "config": {"model": "CVAE", "robot": "Planar", "dof": 6, "len_links": [0.5, 0.5, 0.5, 0.5, 0.5, 1.0], "results_dir": "results/", "input_dim": 6, "condition_dim": 2, "latent_dim": 4, "num_layers": 3, "hidden_dim": 200, "num_epochs": 60, "batch_size": 1000, "lr_rate": 0.0041583305116809416, "weight_decay": 1.0073364581245354e-05, "variational_beta": 0.0067, "checkpoint_epoch": 0, "hyperparam_tuning": true}, "time_since_restore": 666.8384137153625, "timesteps_since_restore": 0, "iterations_since_restore": 33, "trial_id": "f6f23_00005"}
{"loss": 50.81030582972935, "epoch": 33, "time_this_iter_s": 19.420485258102417, "done": false, "timesteps_total": null, "episodes_total": null, "training_iteration": 34, "experiment_id": "4705856e011f477eb062cc3ecd55c165", "date": "2021-03-02_23-32-14", "timestamp": 1614727934, "time_total_s": 686.258898973465, "pid": 8500, "hostname": "instance-adlr-2", "node_ip": "10.128.0.5", "config": {"model": "CVAE", "robot": "Planar", "dof": 6, "len_links": [0.5, 0.5, 0.5, 0.5, 0.5, 1.0], "results_dir": "results/", "input_dim": 6, "condition_dim": 2, "latent_dim": 4, "num_layers": 3, "hidden_dim": 200, "num_epochs": 60, "batch_size": 1000, "lr_rate": 0.0041583305116809416, "weight_decay": 1.0073364581245354e-05, "variational_beta": 0.0067, "checkpoint_epoch": 0, "hyperparam_tuning": true}, "time_since_restore": 686.258898973465, "timesteps_since_restore": 0, "iterations_since_restore": 34, "trial_id": "f6f23_00005"}
{"loss": 50.69123541150774, "epoch": 34, "time_this_iter_s": 19.509653091430664, "done": false, "timesteps_total": null, "episodes_total": null, "training_iteration": 35, "experiment_id": "4705856e011f477eb062cc3ecd55c165", "date": "2021-03-02_23-32-33", "timestamp": 1614727953, "time_total_s": 705.7685520648956, "pid": 8500, "hostname": "instance-adlr-2", "node_ip": "10.128.0.5", "config": {"model": "CVAE", "robot": "Planar", "dof": 6, "len_links": [0.5, 0.5, 0.5, 0.5, 0.5, 1.0], "results_dir": "results/", "input_dim": 6, "condition_dim": 2, "latent_dim": 4, "num_layers": 3, "hidden_dim": 200, "num_epochs": 60, "batch_size": 1000, "lr_rate": 0.0041583305116809416, "weight_decay": 1.0073364581245354e-05, "variational_beta": 0.0067, "checkpoint_epoch": 0, "hyperparam_tuning": true}, "time_since_restore": 705.7685520648956, "timesteps_since_restore": 0, "iterations_since_restore": 35, "trial_id": "f6f23_00005"}
{"loss": 50.59090048108782, "epoch": 35, "time_this_iter_s": 19.89851951599121, "done": false, "timesteps_total": null, "episodes_total": null, "training_iteration": 36, "experiment_id": "4705856e011f477eb062cc3ecd55c165", "date": "2021-03-02_23-32-53", "timestamp": 1614727973, "time_total_s": 725.6670715808868, "pid": 8500, "hostname": "instance-adlr-2", "node_ip": "10.128.0.5", "config": {"model": "CVAE", "robot": "Planar", "dof": 6, "len_links": [0.5, 0.5, 0.5, 0.5, 0.5, 1.0], "results_dir": "results/", "input_dim": 6, "condition_dim": 2, "latent_dim": 4, "num_layers": 3, "hidden_dim": 200, "num_epochs": 60, "batch_size": 1000, "lr_rate": 0.0041583305116809416, "weight_decay": 1.0073364581245354e-05, "variational_beta": 0.0067, "checkpoint_epoch": 0, "hyperparam_tuning": true}, "time_since_restore": 725.6670715808868, "timesteps_since_restore": 0, "iterations_since_restore": 36, "trial_id": "f6f23_00005"}
{"loss": 50.56759583064488, "epoch": 36, "time_this_iter_s": 19.164198398590088, "done": false, "timesteps_total": null, "episodes_total": null, "training_iteration": 37, "experiment_id": "4705856e011f477eb062cc3ecd55c165", "date": "2021-03-02_23-33-13", "timestamp": 1614727993, "time_total_s": 744.8312699794769, "pid": 8500, "hostname": "instance-adlr-2", "node_ip": "10.128.0.5", "config": {"model": "CVAE", "robot": "Planar", "dof": 6, "len_links": [0.5, 0.5, 0.5, 0.5, 0.5, 1.0], "results_dir": "results/", "input_dim": 6, "condition_dim": 2, "latent_dim": 4, "num_layers": 3, "hidden_dim": 200, "num_epochs": 60, "batch_size": 1000, "lr_rate": 0.0041583305116809416, "weight_decay": 1.0073364581245354e-05, "variational_beta": 0.0067, "checkpoint_epoch": 0, "hyperparam_tuning": true}, "time_since_restore": 744.8312699794769, "timesteps_since_restore": 0, "iterations_since_restore": 37, "trial_id": "f6f23_00005"}
{"loss": 50.49803361620222, "epoch": 37, "time_this_iter_s": 19.447988748550415, "done": false, "timesteps_total": null, "episodes_total": null, "training_iteration": 38, "experiment_id": "4705856e011f477eb062cc3ecd55c165", "date": "2021-03-02_23-33-32", "timestamp": 1614728012, "time_total_s": 764.2792587280273, "pid": 8500, "hostname": "instance-adlr-2", "node_ip": "10.128.0.5", "config": {"model": "CVAE", "robot": "Planar", "dof": 6, "len_links": [0.5, 0.5, 0.5, 0.5, 0.5, 1.0], "results_dir": "results/", "input_dim": 6, "condition_dim": 2, "latent_dim": 4, "num_layers": 3, "hidden_dim": 200, "num_epochs": 60, "batch_size": 1000, "lr_rate": 0.0041583305116809416, "weight_decay": 1.0073364581245354e-05, "variational_beta": 0.0067, "checkpoint_epoch": 0, "hyperparam_tuning": true}, "time_since_restore": 764.2792587280273, "timesteps_since_restore": 0, "iterations_since_restore": 38, "trial_id": "f6f23_00005"}
{"loss": 50.446877980913435, "epoch": 38, "time_this_iter_s": 19.285679817199707, "done": false, "timesteps_total": null, "episodes_total": null, "training_iteration": 39, "experiment_id": "4705856e011f477eb062cc3ecd55c165", "date": "2021-03-02_23-33-51", "timestamp": 1614728031, "time_total_s": 783.564938545227, "pid": 8500, "hostname": "instance-adlr-2", "node_ip": "10.128.0.5", "config": {"model": "CVAE", "robot": "Planar", "dof": 6, "len_links": [0.5, 0.5, 0.5, 0.5, 0.5, 1.0], "results_dir": "results/", "input_dim": 6, "condition_dim": 2, "latent_dim": 4, "num_layers": 3, "hidden_dim": 200, "num_epochs": 60, "batch_size": 1000, "lr_rate": 0.0041583305116809416, "weight_decay": 1.0073364581245354e-05, "variational_beta": 0.0067, "checkpoint_epoch": 0, "hyperparam_tuning": true}, "time_since_restore": 783.564938545227, "timesteps_since_restore": 0, "iterations_since_restore": 39, "trial_id": "f6f23_00005"}
{"loss": 50.40961583818708, "epoch": 39, "time_this_iter_s": 19.43637442588806, "done": false, "timesteps_total": null, "episodes_total": null, "training_iteration": 40, "experiment_id": "4705856e011f477eb062cc3ecd55c165", "date": "2021-03-02_23-34-11", "timestamp": 1614728051, "time_total_s": 803.0013129711151, "pid": 8500, "hostname": "instance-adlr-2", "node_ip": "10.128.0.5", "config": {"model": "CVAE", "robot": "Planar", "dof": 6, "len_links": [0.5, 0.5, 0.5, 0.5, 0.5, 1.0], "results_dir": "results/", "input_dim": 6, "condition_dim": 2, "latent_dim": 4, "num_layers": 3, "hidden_dim": 200, "num_epochs": 60, "batch_size": 1000, "lr_rate": 0.0041583305116809416, "weight_decay": 1.0073364581245354e-05, "variational_beta": 0.0067, "checkpoint_epoch": 0, "hyperparam_tuning": true}, "time_since_restore": 803.0013129711151, "timesteps_since_restore": 0, "iterations_since_restore": 40, "trial_id": "f6f23_00005"}
{"loss": 50.354287665230885, "epoch": 40, "time_this_iter_s": 20.049890756607056, "done": false, "timesteps_total": null, "episodes_total": null, "training_iteration": 41, "experiment_id": "4705856e011f477eb062cc3ecd55c165", "date": "2021-03-02_23-34-31", "timestamp": 1614728071, "time_total_s": 823.0512037277222, "pid": 8500, "hostname": "instance-adlr-2", "node_ip": "10.128.0.5", "config": {"model": "CVAE", "robot": "Planar", "dof": 6, "len_links": [0.5, 0.5, 0.5, 0.5, 0.5, 1.0], "results_dir": "results/", "input_dim": 6, "condition_dim": 2, "latent_dim": 4, "num_layers": 3, "hidden_dim": 200, "num_epochs": 60, "batch_size": 1000, "lr_rate": 0.0041583305116809416, "weight_decay": 1.0073364581245354e-05, "variational_beta": 0.0067, "checkpoint_epoch": 0, "hyperparam_tuning": true}, "time_since_restore": 823.0512037277222, "timesteps_since_restore": 0, "iterations_since_restore": 41, "trial_id": "f6f23_00005"}
{"loss": 50.32111488342285, "epoch": 41, "time_this_iter_s": 20.030125617980957, "done": false, "timesteps_total": null, "episodes_total": null, "training_iteration": 42, "experiment_id": "4705856e011f477eb062cc3ecd55c165", "date": "2021-03-02_23-34-51", "timestamp": 1614728091, "time_total_s": 843.0813293457031, "pid": 8500, "hostname": "instance-adlr-2", "node_ip": "10.128.0.5", "config": {"model": "CVAE", "robot": "Planar", "dof": 6, "len_links": [0.5, 0.5, 0.5, 0.5, 0.5, 1.0], "results_dir": "results/", "input_dim": 6, "condition_dim": 2, "latent_dim": 4, "num_layers": 3, "hidden_dim": 200, "num_epochs": 60, "batch_size": 1000, "lr_rate": 0.0041583305116809416, "weight_decay": 1.0073364581245354e-05, "variational_beta": 0.0067, "checkpoint_epoch": 0, "hyperparam_tuning": true}, "time_since_restore": 843.0813293457031, "timesteps_since_restore": 0, "iterations_since_restore": 42, "trial_id": "f6f23_00005"}
{"loss": 50.273921078273226, "epoch": 42, "time_this_iter_s": 19.703343629837036, "done": false, "timesteps_total": null, "episodes_total": null, "training_iteration": 43, "experiment_id": "4705856e011f477eb062cc3ecd55c165", "date": "2021-03-02_23-35-10", "timestamp": 1614728110, "time_total_s": 862.7846729755402, "pid": 8500, "hostname": "instance-adlr-2", "node_ip": "10.128.0.5", "config": {"model": "CVAE", "robot": "Planar", "dof": 6, "len_links": [0.5, 0.5, 0.5, 0.5, 0.5, 1.0], "results_dir": "results/", "input_dim": 6, "condition_dim": 2, "latent_dim": 4, "num_layers": 3, "hidden_dim": 200, "num_epochs": 60, "batch_size": 1000, "lr_rate": 0.0041583305116809416, "weight_decay": 1.0073364581245354e-05, "variational_beta": 0.0067, "checkpoint_epoch": 0, "hyperparam_tuning": true}, "time_since_restore": 862.7846729755402, "timesteps_since_restore": 0, "iterations_since_restore": 43, "trial_id": "f6f23_00005"}
{"loss": 50.208480475289484, "epoch": 43, "time_this_iter_s": 19.290314197540283, "done": false, "timesteps_total": null, "episodes_total": null, "training_iteration": 44, "experiment_id": "4705856e011f477eb062cc3ecd55c165", "date": "2021-03-02_23-35-30", "timestamp": 1614728130, "time_total_s": 882.0749871730804, "pid": 8500, "hostname": "instance-adlr-2", "node_ip": "10.128.0.5", "config": {"model": "CVAE", "robot": "Planar", "dof": 6, "len_links": [0.5, 0.5, 0.5, 0.5, 0.5, 1.0], "results_dir": "results/", "input_dim": 6, "condition_dim": 2, "latent_dim": 4, "num_layers": 3, "hidden_dim": 200, "num_epochs": 60, "batch_size": 1000, "lr_rate": 0.0041583305116809416, "weight_decay": 1.0073364581245354e-05, "variational_beta": 0.0067, "checkpoint_epoch": 0, "hyperparam_tuning": true}, "time_since_restore": 882.0749871730804, "timesteps_since_restore": 0, "iterations_since_restore": 44, "trial_id": "f6f23_00005"}
{"loss": 50.19392158508301, "epoch": 44, "time_this_iter_s": 20.22463822364807, "done": false, "timesteps_total": null, "episodes_total": null, "training_iteration": 45, "experiment_id": "4705856e011f477eb062cc3ecd55c165", "date": "2021-03-02_23-35-50", "timestamp": 1614728150, "time_total_s": 902.2996253967285, "pid": 8500, "hostname": "instance-adlr-2", "node_ip": "10.128.0.5", "config": {"model": "CVAE", "robot": "Planar", "dof": 6, "len_links": [0.5, 0.5, 0.5, 0.5, 0.5, 1.0], "results_dir": "results/", "input_dim": 6, "condition_dim": 2, "latent_dim": 4, "num_layers": 3, "hidden_dim": 200, "num_epochs": 60, "batch_size": 1000, "lr_rate": 0.0041583305116809416, "weight_decay": 1.0073364581245354e-05, "variational_beta": 0.0067, "checkpoint_epoch": 0, "hyperparam_tuning": true}, "time_since_restore": 902.2996253967285, "timesteps_since_restore": 0, "iterations_since_restore": 45, "trial_id": "f6f23_00005"}
{"loss": 50.14403502328055, "epoch": 45, "time_this_iter_s": 19.859607934951782, "done": false, "timesteps_total": null, "episodes_total": null, "training_iteration": 46, "experiment_id": "4705856e011f477eb062cc3ecd55c165", "date": "2021-03-02_23-36-10", "timestamp": 1614728170, "time_total_s": 922.1592333316803, "pid": 8500, "hostname": "instance-adlr-2", "node_ip": "10.128.0.5", "config": {"model": "CVAE", "robot": "Planar", "dof": 6, "len_links": [0.5, 0.5, 0.5, 0.5, 0.5, 1.0], "results_dir": "results/", "input_dim": 6, "condition_dim": 2, "latent_dim": 4, "num_layers": 3, "hidden_dim": 200, "num_epochs": 60, "batch_size": 1000, "lr_rate": 0.0041583305116809416, "weight_decay": 1.0073364581245354e-05, "variational_beta": 0.0067, "checkpoint_epoch": 0, "hyperparam_tuning": true}, "time_since_restore": 922.1592333316803, "timesteps_since_restore": 0, "iterations_since_restore": 46, "trial_id": "f6f23_00005"}
{"loss": 50.16244603293283, "epoch": 46, "time_this_iter_s": 19.996745347976685, "done": false, "timesteps_total": null, "episodes_total": null, "training_iteration": 47, "experiment_id": "4705856e011f477eb062cc3ecd55c165", "date": "2021-03-02_23-36-30", "timestamp": 1614728190, "time_total_s": 942.155978679657, "pid": 8500, "hostname": "instance-adlr-2", "node_ip": "10.128.0.5", "config": {"model": "CVAE", "robot": "Planar", "dof": 6, "len_links": [0.5, 0.5, 0.5, 0.5, 0.5, 1.0], "results_dir": "results/", "input_dim": 6, "condition_dim": 2, "latent_dim": 4, "num_layers": 3, "hidden_dim": 200, "num_epochs": 60, "batch_size": 1000, "lr_rate": 0.0041583305116809416, "weight_decay": 1.0073364581245354e-05, "variational_beta": 0.0067, "checkpoint_epoch": 0, "hyperparam_tuning": true}, "time_since_restore": 942.155978679657, "timesteps_since_restore": 0, "iterations_since_restore": 47, "trial_id": "f6f23_00005"}
{"loss": 50.11789681025914, "epoch": 47, "time_this_iter_s": 19.567912101745605, "done": false, "timesteps_total": null, "episodes_total": null, "training_iteration": 48, "experiment_id": "4705856e011f477eb062cc3ecd55c165", "date": "2021-03-02_23-36-49", "timestamp": 1614728209, "time_total_s": 961.7238907814026, "pid": 8500, "hostname": "instance-adlr-2", "node_ip": "10.128.0.5", "config": {"model": "CVAE", "robot": "Planar", "dof": 6, "len_links": [0.5, 0.5, 0.5, 0.5, 0.5, 1.0], "results_dir": "results/", "input_dim": 6, "condition_dim": 2, "latent_dim": 4, "num_layers": 3, "hidden_dim": 200, "num_epochs": 60, "batch_size": 1000, "lr_rate": 0.0041583305116809416, "weight_decay": 1.0073364581245354e-05, "variational_beta": 0.0067, "checkpoint_epoch": 0, "hyperparam_tuning": true}, "time_since_restore": 961.7238907814026, "timesteps_since_restore": 0, "iterations_since_restore": 48, "trial_id": "f6f23_00005"}
{"loss": 50.10493531363351, "epoch": 48, "time_this_iter_s": 19.23885226249695, "done": false, "timesteps_total": null, "episodes_total": null, "training_iteration": 49, "experiment_id": "4705856e011f477eb062cc3ecd55c165", "date": "2021-03-02_23-37-09", "timestamp": 1614728229, "time_total_s": 980.9627430438995, "pid": 8500, "hostname": "instance-adlr-2", "node_ip": "10.128.0.5", "config": {"model": "CVAE", "robot": "Planar", "dof": 6, "len_links": [0.5, 0.5, 0.5, 0.5, 0.5, 1.0], "results_dir": "results/", "input_dim": 6, "condition_dim": 2, "latent_dim": 4, "num_layers": 3, "hidden_dim": 200, "num_epochs": 60, "batch_size": 1000, "lr_rate": 0.0041583305116809416, "weight_decay": 1.0073364581245354e-05, "variational_beta": 0.0067, "checkpoint_epoch": 0, "hyperparam_tuning": true}, "time_since_restore": 980.9627430438995, "timesteps_since_restore": 0, "iterations_since_restore": 49, "trial_id": "f6f23_00005"}
{"loss": 50.09197215488979, "epoch": 49, "time_this_iter_s": 20.22995138168335, "done": false, "timesteps_total": null, "episodes_total": null, "training_iteration": 50, "experiment_id": "4705856e011f477eb062cc3ecd55c165", "date": "2021-03-02_23-37-29", "timestamp": 1614728249, "time_total_s": 1001.1926944255829, "pid": 8500, "hostname": "instance-adlr-2", "node_ip": "10.128.0.5", "config": {"model": "CVAE", "robot": "Planar", "dof": 6, "len_links": [0.5, 0.5, 0.5, 0.5, 0.5, 1.0], "results_dir": "results/", "input_dim": 6, "condition_dim": 2, "latent_dim": 4, "num_layers": 3, "hidden_dim": 200, "num_epochs": 60, "batch_size": 1000, "lr_rate": 0.0041583305116809416, "weight_decay": 1.0073364581245354e-05, "variational_beta": 0.0067, "checkpoint_epoch": 0, "hyperparam_tuning": true}, "time_since_restore": 1001.1926944255829, "timesteps_since_restore": 0, "iterations_since_restore": 50, "trial_id": "f6f23_00005"}
{"loss": 50.05456594194685, "epoch": 50, "time_this_iter_s": 19.9353768825531, "done": false, "timesteps_total": null, "episodes_total": null, "training_iteration": 51, "experiment_id": "4705856e011f477eb062cc3ecd55c165", "date": "2021-03-02_23-37-49", "timestamp": 1614728269, "time_total_s": 1021.128071308136, "pid": 8500, "hostname": "instance-adlr-2", "node_ip": "10.128.0.5", "config": {"model": "CVAE", "robot": "Planar", "dof": 6, "len_links": [0.5, 0.5, 0.5, 0.5, 0.5, 1.0], "results_dir": "results/", "input_dim": 6, "condition_dim": 2, "latent_dim": 4, "num_layers": 3, "hidden_dim": 200, "num_epochs": 60, "batch_size": 1000, "lr_rate": 0.0041583305116809416, "weight_decay": 1.0073364581245354e-05, "variational_beta": 0.0067, "checkpoint_epoch": 0, "hyperparam_tuning": true}, "time_since_restore": 1021.128071308136, "timesteps_since_restore": 0, "iterations_since_restore": 51, "trial_id": "f6f23_00005"}
{"loss": 50.019582655770435, "epoch": 51, "time_this_iter_s": 20.513817071914673, "done": false, "timesteps_total": null, "episodes_total": null, "training_iteration": 52, "experiment_id": "4705856e011f477eb062cc3ecd55c165", "date": "2021-03-02_23-38-09", "timestamp": 1614728289, "time_total_s": 1041.6418883800507, "pid": 8500, "hostname": "instance-adlr-2", "node_ip": "10.128.0.5", "config": {"model": "CVAE", "robot": "Planar", "dof": 6, "len_links": [0.5, 0.5, 0.5, 0.5, 0.5, 1.0], "results_dir": "results/", "input_dim": 6, "condition_dim": 2, "latent_dim": 4, "num_layers": 3, "hidden_dim": 200, "num_epochs": 60, "batch_size": 1000, "lr_rate": 0.0041583305116809416, "weight_decay": 1.0073364581245354e-05, "variational_beta": 0.0067, "checkpoint_epoch": 0, "hyperparam_tuning": true}, "time_since_restore": 1041.6418883800507, "timesteps_since_restore": 0, "iterations_since_restore": 52, "trial_id": "f6f23_00005"}
{"loss": 49.9931131199428, "epoch": 52, "time_this_iter_s": 19.81022572517395, "done": false, "timesteps_total": null, "episodes_total": null, "training_iteration": 53, "experiment_id": "4705856e011f477eb062cc3ecd55c165", "date": "2021-03-02_23-38-29", "timestamp": 1614728309, "time_total_s": 1061.4521141052246, "pid": 8500, "hostname": "instance-adlr-2", "node_ip": "10.128.0.5", "config": {"model": "CVAE", "robot": "Planar", "dof": 6, "len_links": [0.5, 0.5, 0.5, 0.5, 0.5, 1.0], "results_dir": "results/", "input_dim": 6, "condition_dim": 2, "latent_dim": 4, "num_layers": 3, "hidden_dim": 200, "num_epochs": 60, "batch_size": 1000, "lr_rate": 0.0041583305116809416, "weight_decay": 1.0073364581245354e-05, "variational_beta": 0.0067, "checkpoint_epoch": 0, "hyperparam_tuning": true}, "time_since_restore": 1061.4521141052246, "timesteps_since_restore": 0, "iterations_since_restore": 53, "trial_id": "f6f23_00005"}
{"loss": 49.988887645176476, "epoch": 53, "time_this_iter_s": 19.510009288787842, "done": false, "timesteps_total": null, "episodes_total": null, "training_iteration": 54, "experiment_id": "4705856e011f477eb062cc3ecd55c165", "date": "2021-03-02_23-38-49", "timestamp": 1614728329, "time_total_s": 1080.9621233940125, "pid": 8500, "hostname": "instance-adlr-2", "node_ip": "10.128.0.5", "config": {"model": "CVAE", "robot": "Planar", "dof": 6, "len_links": [0.5, 0.5, 0.5, 0.5, 0.5, 1.0], "results_dir": "results/", "input_dim": 6, "condition_dim": 2, "latent_dim": 4, "num_layers": 3, "hidden_dim": 200, "num_epochs": 60, "batch_size": 1000, "lr_rate": 0.0041583305116809416, "weight_decay": 1.0073364581245354e-05, "variational_beta": 0.0067, "checkpoint_epoch": 0, "hyperparam_tuning": true}, "time_since_restore": 1080.9621233940125, "timesteps_since_restore": 0, "iterations_since_restore": 54, "trial_id": "f6f23_00005"}
{"loss": 49.9912400163923, "epoch": 54, "time_this_iter_s": 19.492419242858887, "done": false, "timesteps_total": null, "episodes_total": null, "training_iteration": 55, "experiment_id": "4705856e011f477eb062cc3ecd55c165", "date": "2021-03-02_23-39-08", "timestamp": 1614728348, "time_total_s": 1100.4545426368713, "pid": 8500, "hostname": "instance-adlr-2", "node_ip": "10.128.0.5", "config": {"model": "CVAE", "robot": "Planar", "dof": 6, "len_links": [0.5, 0.5, 0.5, 0.5, 0.5, 1.0], "results_dir": "results/", "input_dim": 6, "condition_dim": 2, "latent_dim": 4, "num_layers": 3, "hidden_dim": 200, "num_epochs": 60, "batch_size": 1000, "lr_rate": 0.0041583305116809416, "weight_decay": 1.0073364581245354e-05, "variational_beta": 0.0067, "checkpoint_epoch": 0, "hyperparam_tuning": true}, "time_since_restore": 1100.4545426368713, "timesteps_since_restore": 0, "iterations_since_restore": 55, "trial_id": "f6f23_00005"}
{"loss": 49.956986013139996, "epoch": 55, "time_this_iter_s": 20.10532236099243, "done": false, "timesteps_total": null, "episodes_total": null, "training_iteration": 56, "experiment_id": "4705856e011f477eb062cc3ecd55c165", "date": "2021-03-02_23-39-28", "timestamp": 1614728368, "time_total_s": 1120.5598649978638, "pid": 8500, "hostname": "instance-adlr-2", "node_ip": "10.128.0.5", "config": {"model": "CVAE", "robot": "Planar", "dof": 6, "len_links": [0.5, 0.5, 0.5, 0.5, 0.5, 1.0], "results_dir": "results/", "input_dim": 6, "condition_dim": 2, "latent_dim": 4, "num_layers": 3, "hidden_dim": 200, "num_epochs": 60, "batch_size": 1000, "lr_rate": 0.0041583305116809416, "weight_decay": 1.0073364581245354e-05, "variational_beta": 0.0067, "checkpoint_epoch": 0, "hyperparam_tuning": true}, "time_since_restore": 1120.5598649978638, "timesteps_since_restore": 0, "iterations_since_restore": 56, "trial_id": "f6f23_00005"}
{"loss": 49.90805406297956, "epoch": 56, "time_this_iter_s": 19.399267196655273, "done": false, "timesteps_total": null, "episodes_total": null, "training_iteration": 57, "experiment_id": "4705856e011f477eb062cc3ecd55c165", "date": "2021-03-02_23-39-48", "timestamp": 1614728388, "time_total_s": 1139.959132194519, "pid": 8500, "hostname": "instance-adlr-2", "node_ip": "10.128.0.5", "config": {"model": "CVAE", "robot": "Planar", "dof": 6, "len_links": [0.5, 0.5, 0.5, 0.5, 0.5, 1.0], "results_dir": "results/", "input_dim": 6, "condition_dim": 2, "latent_dim": 4, "num_layers": 3, "hidden_dim": 200, "num_epochs": 60, "batch_size": 1000, "lr_rate": 0.0041583305116809416, "weight_decay": 1.0073364581245354e-05, "variational_beta": 0.0067, "checkpoint_epoch": 0, "hyperparam_tuning": true}, "time_since_restore": 1139.959132194519, "timesteps_since_restore": 0, "iterations_since_restore": 57, "trial_id": "f6f23_00005"}
{"loss": 49.92685337066651, "epoch": 57, "time_this_iter_s": 19.164135932922363, "done": false, "timesteps_total": null, "episodes_total": null, "training_iteration": 58, "experiment_id": "4705856e011f477eb062cc3ecd55c165", "date": "2021-03-02_23-40-07", "timestamp": 1614728407, "time_total_s": 1159.1232681274414, "pid": 8500, "hostname": "instance-adlr-2", "node_ip": "10.128.0.5", "config": {"model": "CVAE", "robot": "Planar", "dof": 6, "len_links": [0.5, 0.5, 0.5, 0.5, 0.5, 1.0], "results_dir": "results/", "input_dim": 6, "condition_dim": 2, "latent_dim": 4, "num_layers": 3, "hidden_dim": 200, "num_epochs": 60, "batch_size": 1000, "lr_rate": 0.0041583305116809416, "weight_decay": 1.0073364581245354e-05, "variational_beta": 0.0067, "checkpoint_epoch": 0, "hyperparam_tuning": true}, "time_since_restore": 1159.1232681274414, "timesteps_since_restore": 0, "iterations_since_restore": 58, "trial_id": "f6f23_00005"}
{"loss": 49.91235452924456, "epoch": 58, "time_this_iter_s": 20.69305968284607, "done": false, "timesteps_total": null, "episodes_total": null, "training_iteration": 59, "experiment_id": "4705856e011f477eb062cc3ecd55c165", "date": "2021-03-02_23-40-28", "timestamp": 1614728428, "time_total_s": 1179.8163278102875, "pid": 8500, "hostname": "instance-adlr-2", "node_ip": "10.128.0.5", "config": {"model": "CVAE", "robot": "Planar", "dof": 6, "len_links": [0.5, 0.5, 0.5, 0.5, 0.5, 1.0], "results_dir": "results/", "input_dim": 6, "condition_dim": 2, "latent_dim": 4, "num_layers": 3, "hidden_dim": 200, "num_epochs": 60, "batch_size": 1000, "lr_rate": 0.0041583305116809416, "weight_decay": 1.0073364581245354e-05, "variational_beta": 0.0067, "checkpoint_epoch": 0, "hyperparam_tuning": true}, "time_since_restore": 1179.8163278102875, "timesteps_since_restore": 0, "iterations_since_restore": 59, "trial_id": "f6f23_00005"}
{"loss": 49.91536925724574, "epoch": 59, "time_this_iter_s": 18.69247555732727, "done": false, "timesteps_total": null, "episodes_total": null, "training_iteration": 60, "experiment_id": "4705856e011f477eb062cc3ecd55c165", "date": "2021-03-02_23-40-46", "timestamp": 1614728446, "time_total_s": 1198.5088033676147, "pid": 8500, "hostname": "instance-adlr-2", "node_ip": "10.128.0.5", "config": {"model": "CVAE", "robot": "Planar", "dof": 6, "len_links": [0.5, 0.5, 0.5, 0.5, 0.5, 1.0], "results_dir": "results/", "input_dim": 6, "condition_dim": 2, "latent_dim": 4, "num_layers": 3, "hidden_dim": 200, "num_epochs": 60, "batch_size": 1000, "lr_rate": 0.0041583305116809416, "weight_decay": 1.0073364581245354e-05, "variational_beta": 0.0067, "checkpoint_epoch": 0, "hyperparam_tuning": true}, "time_since_restore": 1198.5088033676147, "timesteps_since_restore": 0, "iterations_since_restore": 60, "trial_id": "f6f23_00005"}
